hillmapper/__init__.py
hillmapper/_hillmapper.cpython-313-i386-linux-musl.so
hillmapper.libs/libgcc_s-887de51c.so.1
hillmapper.libs/libstdc++-d6415257.so.6.0.33
hillmapper-0.1.1.dist-info/METADATA
hillmapper-0.1.1.dist-info/WHEEL
hillmapper-0.1.1.dist-info/top_level.txt
hillmapper-0.1.1.dist-info/RECORD
hillmapper-0.1.1.dist-info/licenses/LICENSE
