Metadata-Version: 2.4
Name: hillmapper
Version: 0.1.1
Summary: Hillmapper C++ extension
Author-email: Skander Krid <kridskander@gmail.com>
License-Expression: MIT
Requires-Python: >=3.11
License-File: LICENSE
Dynamic: license-file
